contrasto_trustable-0.1.0.dist-info/METADATA
contrasto_trustable-0.1.0.dist-info/WHEEL
contrasto_trustable-0.1.0.dist-info/entry_points.txt
contrasto_trustable/__init__.py
contrasto_trustable/api/__init__.py
contrasto_trustable/api/api_client.py
contrasto_trustable/api/base_api.py
contrasto_trustable/api/http_client.py
contrasto_trustable/api/injection_check_api.py
contrasto_trustable/config.py
contrasto_trustable/exceptions.py
contrasto_trustable/response_models.py
contrasto_trustable/trustable.py
contrasto_trustable-0.1.0.dist-info/RECORD
